setup.py
py56/ApiAbstract.py
py56/__init__.py
py56/config.py
py56/utils.py
py56.egg-info/PKG-INFO
py56.egg-info/SOURCES.txt
py56.egg-info/dependency_links.txt
py56.egg-info/top_level.txt
py56/user/App2Videos.py
py56/user/__init__.py
py56/video/GetVideoInfo.py
py56/video/VideoAll.py
py56/video/VideoCustom.py
py56/video/__init__.py