Metadata-Version: 1.0
Name: py56
Version: 0.0.4
Summary: Python module for 56 (56Video)
Home-page: http://pythoner.cn
Author: Allan Sun
Author-email: alnsun.cn@gmail.com
License: UNKNOWN
Platform: UNKNOWN
